[
  {
    "type": "function",
    "name": "getRequestsFromId",
    "inputs": [
      {
        "name": "_start",
        "type": "uint256",
        "internalType": "uint256"
      }
    ],
    "outputs": [
      {
        "name": "requestRange",
        "type": "tuple[]",
        "internalType": "struct IApolloCoordinator.PriceFeedRequest[]",
        "components": [
          {
            "name": "requestId",
            "type": "uint256",
            "internalType": "uint256"
          },
          {
            "name": "dataFeedId",
            "type": "string",
            "internalType": "string"
          },
          {
            "name": "callbackGasLimit",
            "type": "uint256",
            "internalType": "uint256"
          },
          {
            "name": "requester",
            "type": "address",
            "internalType": "address"
          }
        ]
      }
    ],
    "stateMutability": "view"
  },
  {
    "type": "function",
    "name": "getRequestsInRange",
    "inputs": [
      {
        "name": "_start",
        "type": "uint256",
        "internalType": "uint256"
      },
      {
        "name": "_end",
        "type": "uint256",
        "internalType": "uint256"
      }
    ],
    "outputs": [
      {
        "name": "requestRange",
        "type": "tuple[]",
        "internalType": "struct IApolloCoordinator.PriceFeedRequest[]",
        "components": [
          {
            "name": "requestId",
            "type": "uint256",
            "internalType": "uint256"
          },
          {
            "name": "dataFeedId",
            "type": "string",
            "internalType": "string"
          },
          {
            "name": "callbackGasLimit",
            "type": "uint256",
            "internalType": "uint256"
          },
          {
            "name": "requester",
            "type": "address",
            "internalType": "address"
          }
        ]
      }
    ],
    "stateMutability": "view"
  },
  {
    "type": "function",
    "name": "requestCounter",
    "inputs": [],
    "outputs": [
      {
        "name": "",
        "type": "uint256",
        "internalType": "uint256"
      }
    ],
    "stateMutability": "view"
  },
  {
    "type": "function",
    "name": "requestDataFeed",
    "inputs": [
      {
        "name": "dataFeedId",
        "type": "string",
        "internalType": "string"
      },
      {
        "name": "callbackGasLimit",
        "type": "uint256",
        "internalType": "uint256"
      }
    ],
    "outputs": [],
    "stateMutability": "nonpayable"
  },
  {
    "type": "function",
    "name": "requests",
    "inputs": [
      {
        "name": "",
        "type": "uint256",
        "internalType": "uint256"
      }
    ],
    "outputs": [
      {
        "name": "requestId",
        "type": "uint256",
        "internalType": "uint256"
      },
      {
        "name": "dataFeedId",
        "type": "string",
        "internalType": "string"
      },
      {
        "name": "callbackGasLimit",
        "type": "uint256",
        "internalType": "uint256"
      },
      {
        "name": "requester",
        "type": "address",
        "internalType": "address"
      }
    ],
    "stateMutability": "view"
  },
  {
    "type": "event",
    "name": "PriceFeedRequested",
    "inputs": [
      {
        "name": "requestId",
        "type": "uint256",
        "indexed": true,
        "internalType": "uint256"
      },
      {
        "name": "dataFeedId",
        "type": "string",
        "indexed": true,
        "internalType": "string"
      },
      {
        "name": "callbackGasLimit",
        "type": "uint256",
        "indexed": false,
        "internalType": "uint256"
      },
      {
        "name": "requester",
        "type": "address",
        "indexed": true,
        "internalType": "address"
      }
    ],
    "anonymous": false
  }
]